widgetastic/__init__.py
widgetastic/browser.py
widgetastic/exceptions.py
widgetastic/log.py
widgetastic/types.py
widgetastic/utils.py
widgetastic/xpath.py
widgetastic/ouia/__init__.py
widgetastic/ouia/checkbox.py
widgetastic/ouia/input.py
widgetastic/ouia/text.py
widgetastic/widget/__init__.py
widgetastic/widget/base.py
widgetastic/widget/checkbox.py
widgetastic/widget/image.py
widgetastic/widget/input.py
widgetastic/widget/select.py
widgetastic/widget/table.py
widgetastic/widget/text.py
widgetastic.core-1.1.0.dist-info/METADATA
widgetastic.core-1.1.0.dist-info/WHEEL
widgetastic.core-1.1.0.dist-info/licenses/LICENSE
widgetastic.core-1.1.0.dist-info/RECORD
