Metadata-Version: 2.4
Name: widgetastic.core
Version: 1.1.0
Summary: Making testing of UIs fantastic.
Project-URL: repository, https://github.com/RedHatQE/widgetastic.core
Maintainer-email: Mike Shriver <mshriver@redhat.com>, Nikhil Dhandre <ndhandre@redhat.com>, Egor Shamardin <eshamard@redhat.com>
License: Copyright 2016 Red Hat, Inc. and/or its affiliates
License-File: LICENSE
Keywords: selenium,widgetastic
Classifier: License :: OSI Approved :: Apache Software License
Classifier: Programming Language :: Python
Classifier: Programming Language :: Python :: 3
Classifier: Programming Language :: Python :: 3.8
Classifier: Programming Language :: Python :: 3.9
Classifier: Programming Language :: Python :: 3.10
Classifier: Programming Language :: Python :: 3.11
Classifier: Programming Language :: Python :: 3.12
Classifier: Programming Language :: Python :: 3.13
Classifier: Programming Language :: Python :: Implementation :: CPython
Classifier: Programming Language :: Python :: Implementation :: PyPy
Classifier: Topic :: Software Development :: Libraries :: Python Modules
Classifier: Topic :: Software Development :: Quality Assurance
Classifier: Topic :: Software Development :: Testing
Requires-Python: >=3.8
Requires-Dist: anytree>=2.9.0
Requires-Dist: cached-property
Requires-Dist: selenium-smart-locator
Requires-Dist: selenium>=4.0.0
Requires-Dist: wait-for
Provides-Extra: dev
Requires-Dist: podman; extra == 'dev'
Requires-Dist: pre-commit; extra == 'dev'
Requires-Dist: pytest; extra == 'dev'
Requires-Dist: pytest-cov; extra == 'dev'
Requires-Dist: pytest-xdist; extra == 'dev'
Provides-Extra: docs
Requires-Dist: sphinx; extra == 'docs'
Provides-Extra: test
Requires-Dist: podman; extra == 'test'
Requires-Dist: pytest; extra == 'test'
Requires-Dist: pytest-cov; extra == 'test'
Requires-Dist: pytest-xdist; extra == 'test'
